{
  "Architecture": [
    "any all"
  ],
  "Binary": [
    "sweep, sweep-dev"
  ],
  "Build-Depends": [
    "debhelper (\u003e= 7), dh-autoreconf, gettext, libasound2-dev [linux-any], libgtk2.0-dev, libmad0-dev, libsamplerate0-dev, libsndfile1-dev, libspeex-dev, libvorbis-dev"
  ],
  "Checksums-Sha256": [
    "596117641f8ae3fa18199f7005871ef5191b968000e23cccbe0144b77383a702 1944 sweep_0.9.3-8.dsc e71ba12d696157170f24c7f00072123f1f78563b42a2ef95bada5dca1633227d 1246176 sweep_0.9.3.orig.tar.gz 4c19b41e5218cefdaf3ae5f169bc4968c48dc477af12455437a06d0a01f1dc31 12853 sweep_0.9.3-8.debian.tar.gz"
  ],
  "Directory": [
    "pool/main/s/sweep"
  ],
  "Files": [
    "8794f015b198a6d6300587c70cba9618 1944 sweep_0.9.3-8.dsc be48e5740a06ee21d3d2bd32231d8f7d 1246176 sweep_0.9.3.orig.tar.gz f0b766a68fad8eb4b8ac2cb5ceaee8e9 12853 sweep_0.9.3-8.debian.tar.gz"
  ],
  "Format": [
    "3.0 (quilt)"
  ],
  "Homepage": [
    "http://www.metadecks.org/software/sweep/"
  ],
  "Maintainer": [
    "Debian QA Group \u003cpackages@qa.debian.org\u003e"
  ],
  "Package": [
    "sweep"
  ],
  "Package-List": [
    "sweep deb sound optional sweep-dev deb devel optional"
  ],
  "Priority": [
    "source"
  ],
  "Section": [
    "sound"
  ],
  "Standards-Version": [
    "3.9.4"
  ],
  "Version": [
    "0.9.3-8"
  ]
}