{
  "Architecture": [
    "all"
  ],
  "Binary": [
    "susv2, susv3, susv4, susv5"
  ],
  "Build-Depends-Indep": [
    "debhelper (\u003e= 10)"
  ],
  "Checksums-Sha256": [
    "18d2b3e603d8b689893b401bbc72c5f584ada6080fe5bc540e51a39c2b5c257c 1540 sus_8.20250128.dsc 45fb58fb3b9f2ff6e381ca91f456817e771ee15423c002b56b5536682b9864d7 4064 sus_8.20250128.tar.xz"
  ],
  "Directory": [
    "pool/contrib/s/sus"
  ],
  "Files": [
    "408114d02d5741ecd050e5ae247d86a3 1540 sus_8.20250128.dsc ea38d43cc5570a30f2423ae15789a9be 4064 sus_8.20250128.tar.xz"
  ],
  "Format": [
    "3.0 (native)"
  ],
  "Maintainer": [
    "David Weinehall \u003ctao@debian.org\u003e"
  ],
  "Package": [
    "sus"
  ],
  "Package-List": [
    "susv2 deb contrib/doc optional arch=all susv3 deb contrib/doc optional arch=all susv4 deb contrib/doc optional arch=all susv5 deb contrib/doc optional arch=all"
  ],
  "Priority": [
    "optional"
  ],
  "Section": [
    "contrib/misc"
  ],
  "Standards-Version": [
    "4.7.0"
  ],
  "Version": [
    "8.20250128"
  ]
}