{
  "Architecture": [
    "any"
  ],
  "Binary": [
    "xrootd-s3-http"
  ],
  "Build-Depends": [
    "debhelper-compat (= 13), cmake, pkgconf, nlohmann-json3-dev, libxrootd-server-dev, libcurl4-openssl-dev, libssl-dev, libtinyxml2-dev, libgtest-dev, curl, openssl, procps, xrootd-server"
  ],
  "Checksums-Sha256": [
    "1419ae1beb696216752e44e1b0100957cd425dc566f9b5068dbf2b4a6693305a 2075 xrootd-s3-http_0.6.6-1.dsc 3e83978d23a7eee931292944986d689c96bc5eb75d1ffcd3d14150332dbc7199 132030 xrootd-s3-http_0.6.6.orig.tar.gz e7e20c247fb3d5018899444f78be003829b57debf55a5b40eae54a70390025d9 2368 xrootd-s3-http_0.6.6-1.debian.tar.xz"
  ],
  "Directory": [
    "pool/main/x/xrootd-s3-http"
  ],
  "Files": [
    "5e5b52c732afbbc15d5b54e44c3a3b72 2075 xrootd-s3-http_0.6.6-1.dsc fd451c822641cff39bd2075884789105 132030 xrootd-s3-http_0.6.6.orig.tar.gz c405880dc52c4f97a93f6c9733380895 2368 xrootd-s3-http_0.6.6-1.debian.tar.xz"
  ],
  "Format": [
    "3.0 (quilt)"
  ],
  "Homepage": [
    "https://github.com/PelicanPlatform/xrootd-s3-http"
  ],
  "Maintainer": [
    "Mattias Ellert \u003cmattias.ellert@physics.uu.se\u003e"
  ],
  "Package": [
    "xrootd-s3-http"
  ],
  "Package-List": [
    "xrootd-s3-http deb libs optional arch=any"
  ],
  "Priority": [
    "optional"
  ],
  "Section": [
    "misc"
  ],
  "Standards-Version": [
    "4.7.4"
  ],
  "Vcs-Browser": [
    "https://salsa.debian.org/ellert/xrootd-s3-http"
  ],
  "Vcs-Git": [
    "https://salsa.debian.org/ellert/xrootd-s3-http.git"
  ],
  "Version": [
    "0.6.6-1"
  ]
}