{
  "Architecture": [
    "all"
  ],
  "Binary": [
    "gyp"
  ],
  "Build-Depends": [
    "debhelper (\u003e= 10~), python (\u003e= 2.6.6-3~), python-setuptools, dh-python, asciidoc, xsltproc, docbook-xsl, docbook-xml"
  ],
  "Checksums-Sha256": [
    "5c962745b5a356d29ceece0fd5beaa371c57a71b9830439656266ff7f00f7655 2111 gyp_0.1+20180428git4d467626-3.dsc bbc49b829d12358351aee3408429b7573c52c45a539cd79a47d94e1350e64372 630886 gyp_0.1+20180428git4d467626.orig.tar.gz 67f00a75dde202872978c7a7d9c770188943b1094f511abe198075d75e1b6dcd 8592 gyp_0.1+20180428git4d467626-3.debian.tar.xz"
  ],
  "Directory": [
    "pool/main/g/gyp"
  ],
  "Files": [
    "aa27dee99ffe5285a7056d573c31f45c 2111 gyp_0.1+20180428git4d467626-3.dsc 084b79ceef268ada04c64c2dd48cb3f4 630886 gyp_0.1+20180428git4d467626.orig.tar.gz 15b723ebf3d0b579a218be092b4f962f 8592 gyp_0.1+20180428git4d467626-3.debian.tar.xz"
  ],
  "Format": [
    "3.0 (quilt)"
  ],
  "Homepage": [
    "https://chromium.googlesource.com/external/gyp/"
  ],
  "Maintainer": [
    "Debian Javascript Maintainers \u003cpkg-javascript-devel@lists.alioth.debian.org\u003e"
  ],
  "Package": [
    "gyp"
  ],
  "Package-List": [
    "gyp deb devel optional arch=all"
  ],
  "Priority": [
    "source"
  ],
  "Section": [
    "python"
  ],
  "Standards-Version": [
    "4.2.1"
  ],
  "Uploaders": [
    "Jérémy Lal \u003ckapouer@melix.org\u003e"
  ],
  "Vcs-Browser": [
    "https://salsa.debian.org/debian/gyp"
  ],
  "Vcs-Git": [
    "https://salsa.debian.org/debian/gyp.git"
  ],
  "Version": [
    "0.1+20180428git4d467626-3"
  ]
}