{
  "Architecture": [
    "any"
  ],
  "Binary": [
    "kinfocenter"
  ],
  "Build-Depends": [
    "cmake (\u003e= 3.16~), debhelper-compat (= 13), dh-sequence-kf5, extra-cmake-modules (\u003e= 5.97~), gettext, libegl-dev, libkf5auth-dev (\u003e= 5.97~), libkf5config-dev (\u003e= 5.97~), libkf5configwidgets-dev (\u003e= 5.97~), libkf5coreaddons-dev (\u003e= 5.97~), libkf5declarative-dev (\u003e= 5.97~), libkf5doctools-dev (\u003e= 5.97~), libkf5i18n-dev (\u003e= 5.97~), libkf5kcmutils-dev (\u003e= 5.97~), libkf5kio-dev (\u003e= 5.97~), libkf5package-dev (\u003e= 5.97~), libkf5service-dev (\u003e= 5.97~), libkf5solid-dev (\u003e= 5.97~), libkf5widgetsaddons-dev (\u003e= 5.97~), libusb-1.0-0-dev, pkg-config, qml-module-org-kde-kirigami2, qtbase5-dev (\u003e= 5.15.2~)"
  ],
  "Checksums-Sha256": [
    "89527399db118791c841c488786d0d8358a88643f555622467d5455f088e3d3c 2837 kinfocenter_5.27.9-1.dsc 03bf74b0b9ccb24fe54cfffa0e18d3498c8722f7e9acc198b3981c2dc54ae862 1016368 kinfocenter_5.27.9.orig.tar.xz 8583dbfa1ec4cc6fdd173a195d2e8ac4956cdb6fee566ce4f69f16e676d4f9d6 833 kinfocenter_5.27.9.orig.tar.xz.asc 84b3a21093f0a446d1f1238f3b74495fe64ceecac203df4ed7c0264a5c17923a 20480 kinfocenter_5.27.9-1.debian.tar.xz"
  ],
  "Directory": [
    "pool/main/k/kinfocenter"
  ],
  "Files": [
    "37b9284a3b639bd76500872e33c373c8 2837 kinfocenter_5.27.9-1.dsc ca83253ccce484f94a4c17a529ba0f82 1016368 kinfocenter_5.27.9.orig.tar.xz f53ab01621f3c87e4c98aada2e19d989 833 kinfocenter_5.27.9.orig.tar.xz.asc 34f56b196cec6b024569cde818ee16ff 20480 kinfocenter_5.27.9-1.debian.tar.xz"
  ],
  "Format": [
    "3.0 (quilt)"
  ],
  "Homepage": [
    "https://invent.kde.org/plasma/kinfocenter"
  ],
  "Maintainer": [
    "Debian Qt/KDE Maintainers \u003cdebian-qt-kde@lists.debian.org\u003e"
  ],
  "Package": [
    "kinfocenter"
  ],
  "Package-List": [
    "kinfocenter deb kde optional arch=any"
  ],
  "Priority": [
    "optional"
  ],
  "Section": [
    "misc"
  ],
  "Standards-Version": [
    "4.6.2"
  ],
  "Uploaders": [
    "Aurélien COUDERC \u003ccoucouf@debian.org\u003e, Patrick Franz \u003cdeltaone@debian.org\u003e,"
  ],
  "Vcs-Browser": [
    "https://salsa.debian.org/qt-kde-team/kde/kinfocenter"
  ],
  "Vcs-Git": [
    "https://salsa.debian.org/qt-kde-team/kde/kinfocenter.git"
  ],
  "Version": [
    "4:5.27.9-1"
  ]
}