{
  "Architecture": [
    "any all"
  ],
  "Binary": [
    "berkeley-express, berkeley-express-doc"
  ],
  "Build-Depends": [
    "debhelper (\u003e= 11~), libboost-thread-dev, libboost-system-dev, libboost-filesystem-dev, libboost-program-options-dev, libboost-date-time-dev, libbamtools-dev, libboost-tools-dev, libgoogle-perftools-dev [amd64 arm64 armel armhf i386 powerpc ppc64el], cmake, libprotobuf-dev, protobuf-compiler"
  ],
  "Checksums-Sha256": [
    "49989f8d25bbcc62670644c9849a72b8aff99796814321c87a18882177d12b88 2426 berkeley-express_1.5.2+dfsg-1.dsc 3bf3ace8b7e22e44417ec5c4e6ee9b95d7cf15ba3038cbe52f2dd71bf28df105 365892 berkeley-express_1.5.2+dfsg.orig.tar.xz f149a22d312dbca06ebb9d0466372da61a40142488eb4af778596ff4b5494c49 8904 berkeley-express_1.5.2+dfsg-1.debian.tar.xz"
  ],
  "Directory": [
    "pool/main/b/berkeley-express"
  ],
  "Files": [
    "f3490f153ddd271e593c274e56d5b4c9 2426 berkeley-express_1.5.2+dfsg-1.dsc f46f67a4d8380852440c9d1ee0c9b7c6 365892 berkeley-express_1.5.2+dfsg.orig.tar.xz 58dab3505fc21116e7bd90f40bf13fac 8904 berkeley-express_1.5.2+dfsg-1.debian.tar.xz"
  ],
  "Format": [
    "3.0 (quilt)"
  ],
  "Homepage": [
    "http://bio.math.berkeley.edu/eXpress/index.html"
  ],
  "Maintainer": [
    "Debian Med Packaging Team \u003cdebian-med-packaging@lists.alioth.debian.org\u003e"
  ],
  "Package": [
    "berkeley-express"
  ],
  "Package-List": [
    "berkeley-express deb science optional arch=any berkeley-express-doc deb doc optional arch=all"
  ],
  "Priority": [
    "optional"
  ],
  "Section": [
    "misc"
  ],
  "Standards-Version": [
    "4.1.3"
  ],
  "Uploaders": [
    "Michael R. Crusoe \u003cmichael.crusoe@gmail.com\u003e"
  ],
  "Vcs-Browser": [
    "https://salsa.debian.org/med-team/berkeley-express"
  ],
  "Vcs-Git": [
    "https://salsa.debian.org/med-team/berkeley-express.git"
  ],
  "Version": [
    "1.5.2+dfsg-1"
  ]
}