{
  "Architecture": [
    "all"
  ],
  "Binary": [
    "php-phpstan-phpdoc-parser"
  ],
  "Build-Depends": [
    "debhelper-compat (= 13), dh-sequence-phpcomposer, php-doctrine-annotations, php-symfony-process, phpab, phpunit"
  ],
  "Checksums-Sha256": [
    "a2616a146bd8b36fc5c2be9f407b92762233130503123c43a7a488d1f12074c7 1982 php-phpstan-phpdoc-parser_1.24.1-1.dsc d20f5aa727ab708ab7925634827a70735649bf5ea55b96072afcef7ba91e234b 149864 php-phpstan-phpdoc-parser_1.24.1.orig.tar.xz 85c01ff07e8735d30283174fee6badc3463a036045f19598674f9c513e59f795 13484 php-phpstan-phpdoc-parser_1.24.1-1.debian.tar.xz"
  ],
  "Directory": [
    "pool/main/p/php-phpstan-phpdoc-parser"
  ],
  "Files": [
    "351932fdb3551e61fd5575e25f7131dd 1982 php-phpstan-phpdoc-parser_1.24.1-1.dsc a1cca7a095d99e9aa8fa04f8d8edf814 149864 php-phpstan-phpdoc-parser_1.24.1.orig.tar.xz b5333636a5ef3b952fd38858560f822e 13484 php-phpstan-phpdoc-parser_1.24.1-1.debian.tar.xz"
  ],
  "Format": [
    "3.0 (quilt)"
  ],
  "Homepage": [
    "https://phpstan.org/"
  ],
  "Maintainer": [
    "Debian PHP PEAR Maintainers \u003cpkg-php-pear@lists.alioth.debian.org\u003e"
  ],
  "Package": [
    "php-phpstan-phpdoc-parser"
  ],
  "Package-List": [
    "php-phpstan-phpdoc-parser deb php optional arch=all"
  ],
  "Priority": [
    "optional"
  ],
  "Section": [
    "misc"
  ],
  "Standards-Version": [
    "4.6.2"
  ],
  "Testsuite": [
    "autopkgtest"
  ],
  "Testsuite-Triggers": [
    "php-doctrine-annotations, php-symfony-process, phpab, phpunit, pkg-php-tools"
  ],
  "Uploaders": [
    "David Prévot \u003ctaffit@debian.org\u003e"
  ],
  "Vcs-Browser": [
    "https://salsa.debian.org/php-team/pear/php-phpstan-phpdoc-parser"
  ],
  "Vcs-Git": [
    "https://salsa.debian.org/php-team/pear/php-phpstan-phpdoc-parser.git"
  ],
  "Version": [
    "1.24.1-1"
  ]
}