{
  "Architecture": [
    "any"
  ],
  "Binary": [
    "tnef"
  ],
  "Build-Depends": [
    "debhelper (\u003e= 9), autotools-dev, quilt, dh-autoreconf"
  ],
  "Checksums-Sha256": [
    "4495edb4e94632137f0fbf68e0faa415909958ec4725574d4fb241f95030b7a6 1916 tnef_1.4.12-1.2+deb10u1.dsc f7dea4c806d2263948ed027dbb8c593191f321b79c73816bb5608c957bc70254 8463407 tnef_1.4.12.orig.tar.gz a1df0161216dd0bbd626bc9820053d2d3efa779aa613887b6c99465bb4d2ea80 8104 tnef_1.4.12-1.2+deb10u1.debian.tar.xz"
  ],
  "Directory": [
    "pool/main/t/tnef"
  ],
  "Files": [
    "8bc73ce4f8d962dc923bbdbdfacb6e7f 1916 tnef_1.4.12-1.2+deb10u1.dsc 59d96464d8aa10349c02ca1edd47f0ac 8463407 tnef_1.4.12.orig.tar.gz d6497b47ceddd3466f8815bff97c8dac 8104 tnef_1.4.12-1.2+deb10u1.debian.tar.xz"
  ],
  "Format": [
    "3.0 (quilt)"
  ],
  "Homepage": [
    "https://github.com/verdammelt/tnef"
  ],
  "Maintainer": [
    "Kevin Coyner \u003ckcoyner@debian.org\u003e"
  ],
  "Package": [
    "tnef"
  ],
  "Package-List": [
    "tnef deb text optional arch=any"
  ],
  "Priority": [
    "source"
  ],
  "Section": [
    "text"
  ],
  "Standards-Version": [
    "3.9.8"
  ],
  "Version": [
    "1.4.12-1.2+deb10u1"
  ]
}