{
  "Architecture": [
    "any"
  ],
  "Binary": [
    "libskbb1, libskbb-dev"
  ],
  "Build-Depends": [
    "debhelper-compat (= 13), d-shlibs, architecture-is-64-bit, architecture-is-little-endian, python3, libopenblas-serial-dev | libblas.so | liblapack.so, liblapacke-dev"
  ],
  "Checksums-Sha256": [
    "9fc4b4e20c0c061d835434159adb7262809b8fc5866f1422fcf8ac016c9d3e3a 2302 scikit-bio-binaries_1.0.3-2.dsc e7b0896b7607439df0fe062581be58c35ee17e7112dc31630b77b01112ffe186 37048 scikit-bio-binaries_1.0.3.orig.tar.gz 7b3b0c3621235aa07cd41cbffc72ff329279d7ba344d85a50a47fada6cc26725 4052 scikit-bio-binaries_1.0.3-2.debian.tar.xz"
  ],
  "Directory": [
    "pool/main/s/scikit-bio-binaries"
  ],
  "Files": [
    "c120610b4ccb9af0e05cb59318a02860 2302 scikit-bio-binaries_1.0.3-2.dsc 452352f657b02f47a581a539cfe90da4 37048 scikit-bio-binaries_1.0.3.orig.tar.gz 5f9398e8440579e43e4b2c5605a39adc 4052 scikit-bio-binaries_1.0.3-2.debian.tar.xz"
  ],
  "Format": [
    "3.0 (quilt)"
  ],
  "Homepage": [
    "https://github.com/scikit-bio/scikit-bio-binaries"
  ],
  "Maintainer": [
    "Debian Med Packaging Team \u003cdebian-med-packaging@lists.alioth.debian.org\u003e"
  ],
  "Package": [
    "scikit-bio-binaries"
  ],
  "Package-List": [
    "libskbb-dev deb libdevel optional arch=any libskbb1 deb libs optional arch=any"
  ],
  "Priority": [
    "optional"
  ],
  "Section": [
    "libdevel"
  ],
  "Standards-Version": [
    "4.7.4"
  ],
  "Testsuite": [
    "autopkgtest"
  ],
  "Testsuite-Triggers": [
    "build-essential"
  ],
  "Uploaders": [
    "Andreas Tille \u003ctille@debian.org\u003e"
  ],
  "Vcs-Browser": [
    "https://salsa.debian.org/med-team/scikit-bio-binaries"
  ],
  "Vcs-Git": [
    "https://salsa.debian.org/med-team/scikit-bio-binaries.git"
  ],
  "Version": [
    "1.0.3-2"
  ]
}