{
  "Architecture": [
    "any all"
  ],
  "Binary": [
    "steghide, steghide-doc"
  ],
  "Build-Depends": [
    "debhelper-compat (= 13), doxygen, libjpeg-dev, libmcrypt-dev, libmhash-dev, libtool-bin, zlib1g-dev"
  ],
  "Checksums-Sha256": [
    "24a764d92f6ef3789b4c9ffb6f2c1284e1d34e793fcea2290e9c1d1ef3e8bb89 2191 steghide_0.5.1+git20240220-1.dsc c6c13ab7401931e1bc7f818af558e1a93b297016c7a5d7fe8a0a853f8f104550 352792 steghide_0.5.1+git20240220.orig.tar.xz 4f3ef366cd3a6cfb5b8dba1f7b5e8580eb0e7c10eb514ecee483c6dac18bddd5 13928 steghide_0.5.1+git20240220-1.debian.tar.xz"
  ],
  "Directory": [
    "pool/main/s/steghide"
  ],
  "Files": [
    "07248633abaf565541c3d7bcd01d07b6 2191 steghide_0.5.1+git20240220-1.dsc e2ecce45ff8dbf2c3e2340291001a812 352792 steghide_0.5.1+git20240220.orig.tar.xz 837da384ba57c73766de9368e2322578 13928 steghide_0.5.1+git20240220-1.debian.tar.xz"
  ],
  "Format": [
    "3.0 (quilt)"
  ],
  "Homepage": [
    "https://steghide.sourceforge.net/"
  ],
  "Maintainer": [
    "Debian Security Tools \u003cteam+pkg-security@tracker.debian.org\u003e"
  ],
  "Package": [
    "steghide"
  ],
  "Package-List": [
    "steghide deb misc optional arch=any steghide-doc deb doc optional arch=all"
  ],
  "Priority": [
    "optional"
  ],
  "Section": [
    "misc"
  ],
  "Standards-Version": [
    "4.7.4"
  ],
  "Testsuite": [
    "autopkgtest"
  ],
  "Uploaders": [
    "Giovani Augusto Ferreira \u003cgiovani@debian.org\u003e"
  ],
  "Vcs-Browser": [
    "https://salsa.debian.org/pkg-security-team/steghide"
  ],
  "Vcs-Git": [
    "https://salsa.debian.org/pkg-security-team/steghide.git"
  ],
  "Version": [
    "0.5.1+git20240220-1"
  ]
}