{
  "Architecture": [
    "any"
  ],
  "Binary": [
    "systemsettings"
  ],
  "Build-Depends": [
    "cmake (\u003e= 3.16~), debhelper-compat (= 13), extra-cmake-modules (\u003e= 5.102.0~), gettext, kirigami2-dev (\u003e= 5.102.0~), libkf5activities-dev (\u003e= 5.102.0~), libkf5activitiesstats-dev (\u003e= 5.101.0~), libkf5auth-dev (\u003e= 5.102.0~), libkf5config-dev (\u003e= 5.102.0~), libkf5crash-dev (\u003e= 5.102.0~), libkf5dbusaddons-dev (\u003e= 5.102.0~), libkf5doctools-dev (\u003e= 5.102.0~), libkf5guiaddons-dev (\u003e= 5.102.0~), libkf5i18n-dev (\u003e= 5.102.0~), libkf5iconthemes-dev (\u003e= 5.102.0~), libkf5itemmodels-dev (\u003e= 5.102.0~), libkf5itemviews-dev (\u003e= 5.102.0~), libkf5kcmutils-dev (\u003e= 5.102.0~), libkf5kio-dev (\u003e= 5.102.0~), libkf5notifications-dev (\u003e= 5.102.0~), libkf5package-dev (\u003e= 5.102.0~), libkf5runner-dev (\u003e= 5.102.0~), libkf5service-dev (\u003e= 5.102.0~), libkf5widgetsaddons-dev (\u003e= 5.102.0~), libkf5windowsystem-dev (\u003e= 5.102.0~), libkf5xmlgui-dev (\u003e= 5.102.0~), pkg-kde-tools (\u003e= 0.15.18~), plasma-workspace-dev (\u003e= 4:5.27.9~), qtbase5-dev (\u003e= 5.15.2~), qtdeclarative5-dev (\u003e= 5.15.2~)"
  ],
  "Checksums-Sha256": [
    "a882c954a7fbbd123d9ad50959e2681ff84719b920ef35377b21716efb645446 3320 systemsettings_5.27.9-1.dsc 4ba52f3abf57cee224071d9ecf1fd0a110b66ba225b81c05bfc0351be2f13861 229080 systemsettings_5.27.9.orig.tar.xz 9401dbbb23838ae8d2230c2b99173e887803cfa7c2e7a5bcd0668a5c06a82a3f 833 systemsettings_5.27.9.orig.tar.xz.asc ab50a31a8ef2a6f98ef30103c60b435733aace6e408679c91a11c6b8eb2d50f7 17116 systemsettings_5.27.9-1.debian.tar.xz"
  ],
  "Directory": [
    "pool/main/s/systemsettings"
  ],
  "Files": [
    "5cbe995bcfd022b7a621d6a62c11a213 3320 systemsettings_5.27.9-1.dsc 4648e981691f9fff7bd9ee3409b42b25 229080 systemsettings_5.27.9.orig.tar.xz 8d704b4d313580675e2332e8125a7ed5 833 systemsettings_5.27.9.orig.tar.xz.asc a1bc06e12e4a3dfdca25cdf335f2d191 17116 systemsettings_5.27.9-1.debian.tar.xz"
  ],
  "Format": [
    "3.0 (quilt)"
  ],
  "Homepage": [
    "https://invent.kde.org/plasma/systemsettings"
  ],
  "Maintainer": [
    "Debian Qt/KDE Maintainers \u003cdebian-qt-kde@lists.debian.org\u003e"
  ],
  "Package": [
    "systemsettings"
  ],
  "Package-List": [
    "systemsettings deb kde optional arch=any"
  ],
  "Priority": [
    "optional"
  ],
  "Section": [
    "misc"
  ],
  "Standards-Version": [
    "4.6.2"
  ],
  "Uploaders": [
    "Aurélien COUDERC \u003ccoucouf@debian.org\u003e, Norbert Preining \u003cnorbert@preining.info\u003e, Patrick Franz \u003cdeltaone@debian.org\u003e, Scarlett Moore \u003csgmoore@kde.org\u003e,"
  ],
  "Vcs-Browser": [
    "https://salsa.debian.org/qt-kde-team/kde/systemsettings"
  ],
  "Vcs-Git": [
    "https://salsa.debian.org/qt-kde-team/kde/systemsettings.git"
  ],
  "Version": [
    "4:5.27.9-1"
  ]
}