{
  "Architecture": [
    "all"
  ],
  "Binary": [
    "python3-streamlink, python3-streamlink-doc, streamlink"
  ],
  "Build-Depends": [
    "debhelper-compat (= 13), dh-sequence-python3, dh-sequence-sphinxdoc, python3, pybuild-plugin-pyproject, python3-setuptools, python3-wheel, python3-certifi, python3-exceptiongroup, python3-isodate, python3-lxml, python3-pycountry, python3-pycryptodome, python3-socks, python3-requests, python3-trio, python3-trio-websocket, python3-urllib3, python3-websocket, python3-docutils, python3-myst-parser, python3-sphinx, furo, python3-sphinx-design, jdupes, python3-freezegun, python3-pytest, python3-pytest-trio, python3-requests-mock"
  ],
  "Checksums-Sha256": [
    "ffea9a5aaa12fe5da1a6535815c0f9477186b10a3488dd8be84e876ef6f0d5df 2936 streamlink_7.1.1-1.dsc c1881ed0bba53612d979d9a918b7dec056fc93cd202a5b07a080e5568dbdab4c 771209 streamlink_7.1.1.orig.tar.gz 01a18f63e54af387816f0b417ffdd219f42f3b04bc0e09bad8d1cc28a04f4e4e 228 streamlink_7.1.1.orig.tar.gz.asc a2c64ee83a18463bc03f9b6c98bf868b4e381123d39d4d4f1a2a4ba681728d65 18068 streamlink_7.1.1-1.debian.tar.xz"
  ],
  "Directory": [
    "pool/main/s/streamlink"
  ],
  "Files": [
    "1e08922c6ece4a34ec0212ee61f2c2d4 2936 streamlink_7.1.1-1.dsc d63b7df26c88c033947b83f5083bebe1 771209 streamlink_7.1.1.orig.tar.gz 906fe6333930f215922fa9bb8bec5284 228 streamlink_7.1.1.orig.tar.gz.asc 5f67ab0df59c07b643b9b73a88a64d27 18068 streamlink_7.1.1-1.debian.tar.xz"
  ],
  "Format": [
    "3.0 (quilt)"
  ],
  "Homepage": [
    "https://streamlink.github.io/"
  ],
  "Maintainer": [
    "Alexis Murzeau \u003camubtdx@gmail.com\u003e"
  ],
  "Package": [
    "streamlink"
  ],
  "Package-List": [
    "python3-streamlink deb python optional arch=all python3-streamlink-doc deb doc optional arch=all streamlink deb video optional arch=all"
  ],
  "Priority": [
    "extra"
  ],
  "Section": [
    "misc"
  ],
  "Standards-Version": [
    "4.7.0"
  ],
  "Testsuite": [
    "autopkgtest"
  ],
  "Testsuite-Triggers": [
    "bash, bsdmainutils, doc-base, man-db, openssl, python3-freezegun, python3-pytest, python3-pytest-trio, python3-requests-mock, python3-setuptools"
  ],
  "Vcs-Browser": [
    "https://salsa.debian.org/amurzeau/streamlink"
  ],
  "Vcs-Git": [
    "https://salsa.debian.org/amurzeau/streamlink.git"
  ],
  "Version": [
    "7.1.1-1"
  ]
}