{
  "Architecture": [
    "all"
  ],
  "Binary": [
    "node-express-rate-limit"
  ],
  "Build-Depends": [
    "debhelper-compat (= 13), dh-sequence-nodejs, dh-nodejs, esbuild, rollup, node-rollup-plugin-dts, node-typescript, node-ip-address (\u003e= 10.2.0~), node-express"
  ],
  "Checksums-Sha256": [
    "61f9c4ceaab0b09e14cc256b2a23fad7593727ebf18aaf994379d7246948180d 2317 node-express-rate-limit_8.5.2-2.dsc 570acae8024c8a0fceb6549e8bdc4949b46510c707ead5b03a7b55d97aa0c8c7 739295 node-express-rate-limit_8.5.2.orig.tar.gz ecb35caee068b63b85d041c489eefb96abe5c0049c798389589a20e4d2e957a1 4124 node-express-rate-limit_8.5.2-2.debian.tar.xz"
  ],
  "Directory": [
    "pool/main/n/node-express-rate-limit"
  ],
  "Files": [
    "b4b74d3a3534d582285f96cff8b6fe24 2317 node-express-rate-limit_8.5.2-2.dsc 322311d8685b41bde53cf53121777c17 739295 node-express-rate-limit_8.5.2.orig.tar.gz 1823985483abe3835bb613d9a1249cf2 4124 node-express-rate-limit_8.5.2-2.debian.tar.xz"
  ],
  "Format": [
    "3.0 (quilt)"
  ],
  "Homepage": [
    "https://github.com/express-rate-limit/express-rate-limit"
  ],
  "Maintainer": [
    "Debian Javascript Maintainers \u003cpkg-javascript-devel@lists.alioth.debian.org\u003e"
  ],
  "Package": [
    "node-express-rate-limit"
  ],
  "Package-List": [
    "node-express-rate-limit deb javascript optional arch=all"
  ],
  "Priority": [
    "optional"
  ],
  "Section": [
    "javascript"
  ],
  "Standards-Version": [
    "4.7.4"
  ],
  "Testsuite": [
    "autopkgtest"
  ],
  "Testsuite-Triggers": [
    "node-express, node-ip-address, nodejs"
  ],
  "Uploaders": [
    "Xavier Guimard \u003cyadd@debian.org\u003e"
  ],
  "Vcs-Browser": [
    "https://salsa.debian.org/js-team/node-express-rate-limit"
  ],
  "Vcs-Git": [
    "https://salsa.debian.org/js-team/node-express-rate-limit.git"
  ],
  "Version": [
    "8.5.2-2"
  ]
}