{
  "Architecture": [
    "any"
  ],
  "Binary": [
    "python3-gsw"
  ],
  "Build-Depends": [
    "debhelper-compat (= 13), dh-sequence-python3, python3-all-dev, python3-numpy, python3-setuptools"
  ],
  "Checksums-Sha256": [
    "5e64da3c3de391727332c99dc1b34a8cee578995c4add670b64a39ebb862fa2f 1965 gsw_3.4.0-1.dsc 9817e9d2124434809da73ba7977331d3df6f040fde3b0f550b7b1a9b9ebaf227 2124976 gsw_3.4.0.orig.tar.xz 40e614b80593ac1b70658f78f41a43b867bbac2007b8bd091510f49509146bad 3880 gsw_3.4.0-1.debian.tar.xz"
  ],
  "Directory": [
    "pool/main/g/gsw"
  ],
  "Files": [
    "1fb20fe06aad95cbf2271b6e6b90e225 1965 gsw_3.4.0-1.dsc 18e8385d54e752b0df4fb994f773f841 2124976 gsw_3.4.0.orig.tar.xz 030cf04d5e2693c7529ab5a10e498357 3880 gsw_3.4.0-1.debian.tar.xz"
  ],
  "Format": [
    "3.0 (quilt)"
  ],
  "Homepage": [
    "https://pypi.python.org/pypi/gsw/"
  ],
  "Maintainer": [
    "Alastair McKinstry \u003cmckinstry@debian.org\u003e"
  ],
  "Package": [
    "gsw"
  ],
  "Package-List": [
    "python3-gsw deb python optional arch=any"
  ],
  "Priority": [
    "source"
  ],
  "Section": [
    "misc"
  ],
  "Standards-Version": [
    "4.5.0"
  ],
  "Uploaders": [
    "Debian Python team \u003cteam+python@tracker.debian.org\u003e"
  ],
  "Vcs-Browser": [
    "https://salsa.debian.org:/science-team/gsw.git"
  ],
  "Vcs-Git": [
    "https://salsa.debian.org:/science-team/gsw.git -b debian/latest"
  ],
  "Version": [
    "3.4.0-1"
  ]
}