{
  "Architecture": [
    "any"
  ],
  "Binary": [
    "ipv6calc"
  ],
  "Build-Depends": [
    "debhelper-compat (= 13), ieee-data, libmaxminddb-dev"
  ],
  "Checksums-Sha256": [
    "0db422509eac49925b40c2df74f5cdfd242fe5ddd6ea617e1a9e7e1ea5a76864 2121 ipv6calc_4.1.0-0.1.dsc 9c42edd9998f13465d275a3124cfdf72c93fd793d38f6d732124ac3f4b84e36e 1801451 ipv6calc_4.1.0.orig.tar.gz 2275223221abb0955a518c60bafb695fb189fe1dfe1bd94cdf100a7c696fc2e9 833 ipv6calc_4.1.0.orig.tar.gz.asc 7a111e908d1f33204c4bbb8ce376cdf6c2499c15374d34ca0c024da663386084 11352 ipv6calc_4.1.0-0.1.debian.tar.xz"
  ],
  "Directory": [
    "pool/main/i/ipv6calc"
  ],
  "Files": [
    "864824343ff38e097d5b8f114eae91c9 2121 ipv6calc_4.1.0-0.1.dsc 4891e8f53606c78c77a8185fe1b02fde 1801451 ipv6calc_4.1.0.orig.tar.gz 0b4590c179eb4c22b92457b9251317d3 833 ipv6calc_4.1.0.orig.tar.gz.asc 635afda12b38b2fb25853cefe97843d0 11352 ipv6calc_4.1.0-0.1.debian.tar.xz"
  ],
  "Format": [
    "3.0 (quilt)"
  ],
  "Homepage": [
    "https://www.deepspace6.net/projects/ipv6calc.html"
  ],
  "Maintainer": [
    "Luca Bruno \u003clucab@debian.org\u003e"
  ],
  "Package": [
    "ipv6calc"
  ],
  "Package-List": [
    "ipv6calc deb net optional arch=any"
  ],
  "Priority": [
    "source"
  ],
  "Section": [
    "net"
  ],
  "Standards-Version": [
    "4.6.2"
  ],
  "Vcs-Browser": [
    "https://salsa.debian.org/debian/ipv6calc"
  ],
  "Vcs-Git": [
    "https://salsa.debian.org/debian/ipv6calc.git"
  ],
  "Version": [
    "4.1.0-0.1"
  ]
}