{
  "Architecture": [
    "all"
  ],
  "Binary": [
    "libfortran-format-perl"
  ],
  "Build-Depends": [
    "debhelper (\u003e= 9)"
  ],
  "Build-Depends-Indep": [
    "perl"
  ],
  "Checksums-Sha256": [
    "50e277f500b92f6186b6f5433be5e6181c4f07542adc188c412ce0814e63230e 2151 libfortran-format-perl_0.90-1.dsc f5ad4047024c665b73ebc0a53dcbdeb70163d3572d9157a7e578f8b864aa2bbe 18324 libfortran-format-perl_0.90.orig.tar.gz 353c725a918a9d9a46acc38c1f5c2dc9e16fbd2a9eac13c332507d5342856949 1652 libfortran-format-perl_0.90-1.debian.tar.xz"
  ],
  "Directory": [
    "pool/main/libf/libfortran-format-perl"
  ],
  "Files": [
    "fbf34c8e9c7618936d5d9edd892285da 2151 libfortran-format-perl_0.90-1.dsc 3456d511830a34114700d0a5176efee9 18324 libfortran-format-perl_0.90.orig.tar.gz 7f41a75319f2c845478df96a842b1aef 1652 libfortran-format-perl_0.90-1.debian.tar.xz"
  ],
  "Format": [
    "3.0 (quilt)"
  ],
  "Homepage": [
    "https://metacpan.org/release/Fortran-Format"
  ],
  "Maintainer": [
    "Debian Perl Group \u003cpkg-perl-maintainers@lists.alioth.debian.org\u003e"
  ],
  "Package": [
    "libfortran-format-perl"
  ],
  "Package-List": [
    "libfortran-format-perl deb perl optional arch=all"
  ],
  "Priority": [
    "extra"
  ],
  "Section": [
    "misc"
  ],
  "Standards-Version": [
    "4.1.5"
  ],
  "Uploaders": [
    "Francesco Paolo Lovergine \u003cfrankie@debian.org\u003e"
  ],
  "Vcs-Browser": [
    "https://salsa.debian.org/perl-team/modules/packages/libfortran-format-perl"
  ],
  "Vcs-Git": [
    "https://salsa.debian.org/perl-team/modules/packages/libfortran-format-perl.git"
  ],
  "Version": [
    "0.90-1"
  ]
}