{
  "Architecture": [
    "all"
  ],
  "Binary": [
    "lomiri-desktop-session, lomiri-desktop, debian-lomiri-default-settings"
  ],
  "Build-Depends": [
    "debhelper-compat (= 13), cmake, dbus-bin, libsystemd-dev [linux-any], pkgconf, systemd-dev"
  ],
  "Checksums-Sha256": [
    "2ff96a969b53c90f08deb1840a558c43cc39d12c9dfe78c0003794bb66af384e 2245 lomiri-session_0.4-2.dsc 4d4370e0534bf415c4ce8a132ad2dd0616c551d5c276b6d2276653d7f80e65be 9580 lomiri-session_0.4.orig.tar.bz2 f3dbf07cf0659cffd841b8dcad18f09301ee94ceb96012bb130b0bf831f01fa2 17376 lomiri-session_0.4-2.debian.tar.xz"
  ],
  "Directory": [
    "pool/main/l/lomiri-session"
  ],
  "Files": [
    "5207dea2f24f6af2a0134b874521607a 2245 lomiri-session_0.4-2.dsc 02127db274f79337ccf2bd13e4ba0dad 9580 lomiri-session_0.4.orig.tar.bz2 8b44b944e1fac31e2ba1cf1f26df5700 17376 lomiri-session_0.4-2.debian.tar.xz"
  ],
  "Format": [
    "3.0 (quilt)"
  ],
  "Homepage": [
    "https://gitlab.com/ubports/development/core/lomiri-session"
  ],
  "Maintainer": [
    "Debian UBports Team \u003cteam+ubports@tracker.debian.org\u003e"
  ],
  "Package": [
    "lomiri-session"
  ],
  "Package-List": [
    "debian-lomiri-default-settings deb x11 optional arch=all lomiri-desktop deb x11 optional arch=all lomiri-desktop-session deb x11 optional arch=all"
  ],
  "Priority": [
    "optional"
  ],
  "Section": [
    "misc"
  ],
  "Standards-Version": [
    "4.7.4"
  ],
  "Uploaders": [
    "Mike Gabriel \u003csunweaver@debian.org\u003e, Marius Gripsgard \u003cmarius@ubports.com\u003e"
  ],
  "Vcs-Browser": [
    "https://salsa.debian.org/ubports-team/lomiri-session"
  ],
  "Vcs-Git": [
    "https://salsa.debian.org/ubports-team/lomiri-session.git"
  ],
  "Version": [
    "0.4-2"
  ]
}