{
  "Architecture": [
    "any"
  ],
  "Binary": [
    "librust-sha256+openssl-dev, librust-sha256+tokio-dev, librust-sha256-dev"
  ],
  "Build-Depends": [
    "cargo:native \u003c!nocheck\u003e, debhelper-compat (= 13), dh-sequence-cargo, librust-async-trait-0.1+default-dev (\u003e= 0.1.68-~~) \u003c!nocheck\u003e, librust-bytes-1+default-dev (\u003e= 1.4.0-~~) \u003c!nocheck\u003e, librust-hex-0.4+default-dev (\u003e= 0.4.2-~~) \u003c!nocheck\u003e, librust-sha2-0.10-dev (\u003e= 0.10.6-~~) \u003c!nocheck\u003e, librust-tokio-1+default-dev (\u003e= 1.28.2-~~) \u003c!nocheck\u003e, librust-tokio-1+fs-dev (\u003e= 1.28.2-~~) \u003c!nocheck\u003e, librust-tokio-1+io-util-dev (\u003e= 1.28.2-~~) \u003c!nocheck\u003e, libstd-rust-dev \u003c!nocheck\u003e, rustc:native \u003c!nocheck\u003e"
  ],
  "Checksums-Sha256": [
    "cd9b167003f711aa668f268ae4b59d33e3535220b563e43b53bcc1cd57feb714 2052 rust-sha256_1.5.0-3.dsc afc1a2a6e3701c40d0f0909c1e1847094b36c33b11e1a83f99727103b5b26b52 9012 rust-sha256_1.5.0.orig.tar.xz db30e51753bec828cb91dd53f3f9926026b7cbeceb347ef94755ed0acedc1527 3168 rust-sha256_1.5.0-3.debian.tar.xz"
  ],
  "Directory": [
    "pool/main/r/rust-sha256"
  ],
  "Files": [
    "9d3c785dcd4a7a0b2f76471fca410423 2052 rust-sha256_1.5.0-3.dsc 36eeaaa7f8d76faf99c1445602cf886e 9012 rust-sha256_1.5.0.orig.tar.xz acf6391db8be0a21bd633f594bbac51f 3168 rust-sha256_1.5.0-3.debian.tar.xz"
  ],
  "Format": [
    "3.0 (quilt)"
  ],
  "Homepage": [
    "https://github.com/baoyachi/sha256-rs"
  ],
  "Maintainer": [
    "Daniel Baumann \u003cdaniel@debian.org\u003e"
  ],
  "Package": [
    "rust-sha256"
  ],
  "Package-List": [
    "librust-sha256+openssl-dev deb rust optional arch=any librust-sha256+tokio-dev deb rust optional arch=any librust-sha256-dev deb rust optional arch=any"
  ],
  "Priority": [
    "optional"
  ],
  "Section": [
    "misc"
  ],
  "Standards-Version": [
    "4.7.0"
  ],
  "Testsuite": [
    "autopkgtest"
  ],
  "Testsuite-Triggers": [
    "dh-cargo, librust-tokio-1+default-dev, librust-tokio-1+full-dev, librust-tokio-test-0.4+default-dev, rustc"
  ],
  "Vcs-Browser": [
    "https://forgejo.debian.net/forgejo/rust-sha256"
  ],
  "Vcs-Git": [
    "https://forgejo.debian.net/forgejo/rust-sha256"
  ],
  "Version": [
    "1.5.0-3"
  ]
}