{
  "Architecture": [
    "any all"
  ],
  "Binary": [
    "libopenjp2-7-dev, libopenjp2-7, openjpeg-doc, libopenjpip7, libopenjpip-dec-server, libopenjpip-viewer, libopenjp2-tools"
  ],
  "Build-Depends": [
    "cmake, debhelper-compat (= 13), dh-apache2 \u003c!pkg.openjpeg2.noapache\u003e, help2man, liblcms2-dev, libpng-dev, libtiff-dev, zlib1g-dev"
  ],
  "Build-Depends-Indep": [
    "default-jdk, doxygen, javahelper, libxerces2-java"
  ],
  "Checksums-Sha256": [
    "f9f15d8400a1ab69381e408ad7ec23c38121efd3a3f50fad5baf514d7df25f9f 2414 openjpeg2_2.5.3-2.dsc 3100f0316e922630112cf6d72c0c20776896e64ad7eab72c2f713c460287eb92 1393716 openjpeg2_2.5.3.orig.tar.xz a1300a5efb9e91f49449b571a3cca04d221f7df5024674cb50c77ca82ec5c65e 14992 openjpeg2_2.5.3-2.debian.tar.xz"
  ],
  "Directory": [
    "pool/main/o/openjpeg2"
  ],
  "Files": [
    "33452c9ec7c573924097dd09c22bd7d5 2414 openjpeg2_2.5.3-2.dsc d12a0697d3af28141fe30bfad119c086 1393716 openjpeg2_2.5.3.orig.tar.xz ca2bf2f70e7e6a68842db2d2550d5a7e 14992 openjpeg2_2.5.3-2.debian.tar.xz"
  ],
  "Format": [
    "3.0 (quilt)"
  ],
  "Homepage": [
    "https://www.openjpeg.org"
  ],
  "Maintainer": [
    "Debian PhotoTools Maintainers \u003cpkg-phototools-devel@lists.alioth.debian.org\u003e"
  ],
  "Package": [
    "openjpeg2"
  ],
  "Package-List": [
    "libopenjp2-7 deb libs optional arch=any libopenjp2-7-dev deb libdevel optional arch=any libopenjp2-tools deb graphics optional arch=any libopenjpip-dec-server deb graphics optional arch=any libopenjpip-viewer deb graphics optional arch=all profile=!pkg.openjpeg2.noapache libopenjpip7 deb libs optional arch=any openjpeg-doc deb doc optional arch=all"
  ],
  "Priority": [
    "optional"
  ],
  "Section": [
    "misc"
  ],
  "Standards-Version": [
    "4.7.0"
  ],
  "Uploaders": [
    "Mathieu Malaterre \u003cmalat@debian.org\u003e"
  ],
  "Vcs-Browser": [
    "https://salsa.debian.org/debian-phototools-team/openjpeg2"
  ],
  "Vcs-Git": [
    "https://salsa.debian.org/debian-phototools-team/openjpeg2.git"
  ],
  "Version": [
    "2.5.3-2"
  ]
}