{
  "Architecture": [
    "all"
  ],
  "Binary": [
    "python3-power"
  ],
  "Build-Depends": [
    "debhelper-compat (= 13), dh-python, python3-all, python3-setuptools"
  ],
  "Checksums-Sha256": [
    "e514e24000ad18ccefcc5f30635ac1b2eda893dca691655a3ef0d8ee577b2638 1952 power_1.4+dfsg-6.dsc e4fd9114c07bd60186a8266c822ae25db0255f32975a9a80b6a4f1ec6650eeec 9295 power_1.4+dfsg.orig.tar.gz 0582aa2286842e9ab3571ae8d812eac24eee45b7682ed2f9556538a9e355f87c 2524 power_1.4+dfsg-6.debian.tar.xz"
  ],
  "Directory": [
    "pool/main/p/power"
  ],
  "Files": [
    "cdf7e87bda36130c2166911fa85c8c48 1952 power_1.4+dfsg-6.dsc 341dc786ca05560ff6a75c6689d86f59 9295 power_1.4+dfsg.orig.tar.gz cd6952181b280404bce5092684ef228a 2524 power_1.4+dfsg-6.debian.tar.xz"
  ],
  "Format": [
    "3.0 (quilt)"
  ],
  "Homepage": [
    "https://github.com/Kentzo/Power"
  ],
  "Maintainer": [
    "Debian Python Team \u003cteam+python@tracker.debian.org\u003e"
  ],
  "Package": [
    "power"
  ],
  "Package-List": [
    "python3-power deb python optional arch=all"
  ],
  "Priority": [
    "source"
  ],
  "Section": [
    "misc"
  ],
  "Standards-Version": [
    "4.6.1"
  ],
  "Uploaders": [
    "Jonathan Carter \u003cjcc@debian.org\u003e"
  ],
  "Vcs-Browser": [
    "https://salsa.debian.org/python-team/packages/power"
  ],
  "Vcs-Git": [
    "https://salsa.debian.org/python-team/packages/power.git"
  ],
  "Version": [
    "1.4+dfsg-6"
  ]
}