{
  "Architecture": [
    "all"
  ],
  "Binary": [
    "fonts-blankenburg"
  ],
  "Build-Depends": [
    "debhelper-compat (= 13)"
  ],
  "Checksums-Sha256": [
    "09c6ff16bebdfa54cf600f32d74e0e1e2b20949370f206b29af0214a91afdba2 1996 fonts-blankenburg_0.1-4.dsc f83c895294a9796a8c55c5376a591d6cf832039768c2460ec57253478e1f7699 126492 fonts-blankenburg_0.1.orig.tar.gz 332b9bc499b0af741b526084a0af82ecee8f5152f5035d23b8fd6708458b8cae 3552 fonts-blankenburg_0.1-4.debian.tar.xz"
  ],
  "Directory": [
    "pool/main/f/fonts-blankenburg"
  ],
  "Files": [
    "fd8ed12f6cf752b776d4c68f72b05da1 1996 fonts-blankenburg_0.1-4.dsc 9c96e865ba75992cdadc4d583cb3e6a7 126492 fonts-blankenburg_0.1.orig.tar.gz 8f86558d6bb5c3ad2bb14b13b239624c 3552 fonts-blankenburg_0.1-4.debian.tar.xz"
  ],
  "Format": [
    "3.0 (quilt)"
  ],
  "Homepage": [
    "http://www.peter-wiegel.de/Blankenburg.html"
  ],
  "Maintainer": [
    "Debian Fonts Task Force \u003cpkg-fonts-devel@lists.alioth.debian.org\u003e"
  ],
  "Package": [
    "fonts-blankenburg"
  ],
  "Package-List": [
    "fonts-blankenburg deb fonts optional arch=all"
  ],
  "Priority": [
    "optional"
  ],
  "Section": [
    "misc"
  ],
  "Standards-Version": [
    "4.7.0"
  ],
  "Uploaders": [
    "Alex Myczko \u003ctar@debian.org\u003e"
  ],
  "Vcs-Browser": [
    "https://salsa.debian.org/fonts-team/fonts-blankenburg"
  ],
  "Vcs-Git": [
    "https://salsa.debian.org/fonts-team/fonts-blankenburg.git"
  ],
  "Version": [
    "0.1-4"
  ]
}