{
  "Architecture": [
    "any all"
  ],
  "Binary": [
    "gcompris-qt, gcompris-qt-data"
  ],
  "Build-Depends": [
    "cmake (\u003e= 3.7~), debhelper-compat (= 13), extra-cmake-modules, libkf5doctools-dev, libqt5charts5-dev (\u003e= 5.12.0~), libqt5sensors5-dev (\u003e= 5.12.0~), libqt5svg5-dev (\u003e= 5.12.0~), pkg-kde-tools, qml-module-qtgraphicaleffects, qml-module-qtmultimedia, qt5-qmake (\u003e= 5.12.0~), qtdeclarative5-dev (\u003e= 5.12.0~), qtmultimedia5-dev (\u003e= 5.12.0~), qtquickcontrols2-5-dev (\u003e= 5.12.0~), qttools5-dev (\u003e= 5.12.0~), qttools5-dev-tools (\u003e= 5.12.0~), xauth \u003c!nocheck\u003e, xvfb \u003c!nocheck\u003e"
  ],
  "Checksums-Sha256": [
    "65129319c4486e2c7ddf4759849e8da345351a042bf76138a6523f72cc45503c 2698 gcompris-qt_4.2-1.dsc 668726abc949c49e5348b55e8b1e7d7005584208432bb95424979f7f08f2256c 49285724 gcompris-qt_4.2.orig.tar.xz 4905038582a81bc4bcd10b445d0d348fbee858e43e3b0b13baf44c979596e532 488 gcompris-qt_4.2.orig.tar.xz.asc ef8fa9fe785b422dceea46540de16bddffab0a0e6cec3796c9128f277c2c482a 41884 gcompris-qt_4.2-1.debian.tar.xz"
  ],
  "Directory": [
    "pool/main/g/gcompris-qt"
  ],
  "Files": [
    "f58731fed807154116b58cd28c58e69b 2698 gcompris-qt_4.2-1.dsc de613b9b516e33e9b19d73000c458d2c 49285724 gcompris-qt_4.2.orig.tar.xz 8a42cd7d95ec31f770be0f13dca343a2 488 gcompris-qt_4.2.orig.tar.xz.asc e26ca16a37c2bf079cf3bc278ec5089f 41884 gcompris-qt_4.2-1.debian.tar.xz"
  ],
  "Format": [
    "3.0 (quilt)"
  ],
  "Homepage": [
    "https://gcompris.net/"
  ],
  "Maintainer": [
    "Debian Qt Extras Team \u003cdebian-qt-kde@lists.debian.org\u003e"
  ],
  "Package": [
    "gcompris-qt"
  ],
  "Package-List": [
    "gcompris-qt deb education optional arch=any gcompris-qt-data deb education optional arch=all"
  ],
  "Priority": [
    "optional"
  ],
  "Section": [
    "misc"
  ],
  "Standards-Version": [
    "4.7.0"
  ],
  "Uploaders": [
    "Simon Quigley \u003ctsimonq2@debian.org\u003e"
  ],
  "Vcs-Browser": [
    "https://salsa.debian.org/qt-kde-team/extras/gcompris-qt"
  ],
  "Vcs-Git": [
    "https://salsa.debian.org/qt-kde-team/extras/gcompris-qt.git"
  ],
  "Version": [
    "4.2-1"
  ]
}