{
  "Architecture": [
    "any all"
  ],
  "Binary": [
    "gnome-recipes, gnome-recipes-data"
  ],
  "Build-Depends": [
    "appstream, debhelper-compat (= 13), itstool, libcanberra-dev, libglib2.0-dev:native, libgnome-autoar-0-dev, libgoa-1.0-dev, libgspell-1-dev, libgtk-3-dev (\u003e= 3.22), libjson-glib-dev, librest-dev, meson (\u003e= 0.36.0), pkgconf"
  ],
  "Checksums-Sha256": [
    "665507012e9197ae48341aea293b3f45423fa846425b861fc3532d8959b48797 2281 gnome-recipes_2.0.4-7.dsc b30e96985f66fe138a17189c77af44d34d0b4c859b304ebdb52033bc2cd3ffed 18166316 gnome-recipes_2.0.4.orig.tar.xz 299a4c7f16983f5bf93deb0eca06b2d810f63e7ca13211695e345c987735fe0b 14224 gnome-recipes_2.0.4-7.debian.tar.xz"
  ],
  "Directory": [
    "pool/main/g/gnome-recipes"
  ],
  "Files": [
    "fef053e43157e759c68c41ecfe9823a1 2281 gnome-recipes_2.0.4-7.dsc 2e854234e88c6320cb167db9bd8270e0 18166316 gnome-recipes_2.0.4.orig.tar.xz 3e3dec408dd4b75b696b6059033a3916 14224 gnome-recipes_2.0.4-7.debian.tar.xz"
  ],
  "Format": [
    "3.0 (quilt)"
  ],
  "Homepage": [
    "https://gitlab.gnome.org/GNOME/recipes"
  ],
  "Maintainer": [
    "Debian GNOME Extras Maintainers \u003cpkg-gnome-extras-maintainers@lists.alioth.debian.org\u003e"
  ],
  "Package": [
    "gnome-recipes"
  ],
  "Package-List": [
    "gnome-recipes deb gnome optional arch=any gnome-recipes-data deb gnome optional arch=all"
  ],
  "Priority": [
    "optional"
  ],
  "Section": [
    "misc"
  ],
  "Standards-Version": [
    "4.7.3"
  ],
  "Uploaders": [
    "Jeremy Bícha \u003cjbicha@ubuntu.com\u003e"
  ],
  "Vcs-Browser": [
    "https://salsa.debian.org/gnome-team/extras/gnome-recipes"
  ],
  "Vcs-Git": [
    "https://salsa.debian.org/gnome-team/extras/gnome-recipes.git"
  ],
  "Version": [
    "2.0.4-7"
  ]
}