{
  "Architecture": [
    "any"
  ],
  "Binary": [
    "phosh-mobile-settings"
  ],
  "Build-Depends": [
    "appstream, debhelper-compat (= 13), desktop-file-utils, libadwaita-1-dev, libgsound-dev, libgtk-4-dev, libsensors-dev, meson, phosh-dev (\u003e= 0.23.0)"
  ],
  "Checksums-Sha256": [
    "a3943ed2365dcd61675d226f7ab103c4b40c317990e2877526a57a4346335802 2257 phosh-mobile-settings_0.30.0-1.dsc 2958f62b88816dbe89ee8b69c832e253d64596eb1234557f11bc3eb2c9abe050 175802 phosh-mobile-settings_0.30.0.orig.tar.gz 47332a738881b5bdb2c340667978e202ed4b44c9f4ede1c4722da4ce90d45e00 3948 phosh-mobile-settings_0.30.0-1.debian.tar.xz"
  ],
  "Directory": [
    "pool/main/p/phosh-mobile-settings"
  ],
  "Files": [
    "bb285b227189193c272f96c49753d0c8 2257 phosh-mobile-settings_0.30.0-1.dsc e2cea86bbc1858597a54f1db90462e9c 175802 phosh-mobile-settings_0.30.0.orig.tar.gz f1c258b427ae5b4e67bc1b0b995cc114 3948 phosh-mobile-settings_0.30.0-1.debian.tar.xz"
  ],
  "Format": [
    "3.0 (quilt)"
  ],
  "Homepage": [
    "https://gitlab.gnome.org/guidog/phosh-mobile-settings/"
  ],
  "Maintainer": [
    "DebianOnMobile Maintainers \u003cdebian-on-mobile-maintainers@alioth-lists.debian.net\u003e"
  ],
  "Package": [
    "phosh-mobile-settings"
  ],
  "Package-List": [
    "phosh-mobile-settings deb x11 optional arch=any"
  ],
  "Priority": [
    "optional"
  ],
  "Section": [
    "misc"
  ],
  "Standards-Version": [
    "4.6.2"
  ],
  "Testsuite": [
    "autopkgtest"
  ],
  "Uploaders": [
    "Guido Günther \u003cagx@sigxcpu.org\u003e,"
  ],
  "Vcs-Browser": [
    "https://salsa.debian.org/DebianOnMobile-team/phosh-mobile-settings"
  ],
  "Vcs-Git": [
    "https://salsa.debian.org/DebianOnMobile-team/phosh-mobile-settings.git"
  ],
  "Version": [
    "0.30.0-1"
  ]
}