{
  "Architecture": [
    "any all"
  ],
  "Binary": [
    "libghc-alsa-core-dev, libghc-alsa-core-prof, libghc-alsa-core-doc"
  ],
  "Build-Depends": [
    "debhelper (\u003e= 10), haskell-devscripts-minimal | haskell-devscripts (\u003e= 0.8), cdbs, ghc (\u003e= 9.4), ghc-prof, libghc-extensible-exceptions-dev (\u003e= 0.1.1), libghc-extensible-exceptions-dev (\u003c\u003c 0.2), libghc-extensible-exceptions-prof (\u003e= 0.1.1), libghc-extensible-exceptions-prof (\u003c\u003c 0.2), libasound2-dev (\u003e= 1.0.1.4), pkg-config"
  ],
  "Build-Depends-Indep": [
    "ghc-doc, libghc-extensible-exceptions-doc"
  ],
  "Checksums-Sha256": [
    "893ce4da650c01da98648ef0941e5821f298d5938dd21fe8535780b8fd5b07a6 2438 haskell-alsa-core_0.5.0.1-8.dsc eb50495ef05ecc7c06a0147da7f0d3efde832a44d23caaf5172dc114882270ab 2668 haskell-alsa-core_0.5.0.1.orig.tar.gz deeeda12b6237b0a5434991f9e002810730e7dd7fc7379a4ee23b633771f27b1 2404 haskell-alsa-core_0.5.0.1-8.debian.tar.xz"
  ],
  "Directory": [
    "pool/main/h/haskell-alsa-core"
  ],
  "Files": [
    "c0779f3ab78b1058cb2c069c7cb2b83a 2438 haskell-alsa-core_0.5.0.1-8.dsc 60af8328663a5d6ecaaf92dd32cf0710 2668 haskell-alsa-core_0.5.0.1.orig.tar.gz e3134d8d838f33be8be3e4f99b48674e 2404 haskell-alsa-core_0.5.0.1-8.debian.tar.xz"
  ],
  "Format": [
    "3.0 (quilt)"
  ],
  "Homepage": [
    "http://www.haskell.org/haskellwiki/ALSA"
  ],
  "Maintainer": [
    "Debian Haskell Group \u003cpkg-haskell-maintainers@lists.alioth.debian.org\u003e"
  ],
  "Package": [
    "haskell-alsa-core"
  ],
  "Package-List": [
    "libghc-alsa-core-dev deb haskell optional arch=any libghc-alsa-core-doc deb doc optional arch=all libghc-alsa-core-prof deb haskell optional arch=any"
  ],
  "Priority": [
    "extra"
  ],
  "Section": [
    "misc"
  ],
  "Standards-Version": [
    "4.6.2"
  ],
  "Uploaders": [
    "Clint Adams \u003cclint@debian.org\u003e"
  ],
  "Version": [
    "0.5.0.1-8"
  ]
}