{
  "Architecture": [
    "all"
  ],
  "Binary": [
    "libhyena-cil, libhyena-cil-dev, monodoc-hyena-manual"
  ],
  "Build-Depends": [
    "debhelper (\u003e= 7.0.50), dh-autoreconf, autotools-dev, cli-common-dev (\u003e= 0.5.7), mono-devel (\u003e= 2.4.2), monodoc-base, libgtk2.0-cil-dev, pkg-config"
  ],
  "Checksums-Sha256": [
    "2113402bbc6160b04c4cf16e5e902990df8a252450aef5b2a407eb4a351e8b6f 1803 hyena_0.5-4.dsc 3b9ba5f412e06f3183fdaca29c47bded55ea1af8b230ad9475a981c994ed81aa 363351 hyena_0.5.orig.tar.gz 381d02ef3bf859df952645106830a140da509c5b4a26990ff0535163518cbd89 5664 hyena_0.5-4.debian.tar.xz"
  ],
  "Directory": [
    "pool/main/h/hyena"
  ],
  "Files": [
    "cbac7bc6da61d969e72254873d0f2b9d 1803 hyena_0.5-4.dsc bc20d11a387e8b09db638922a3cd0eb8 363351 hyena_0.5.orig.tar.gz 298c9b2aa7ee695444e2520599c79fd6 5664 hyena_0.5-4.debian.tar.xz"
  ],
  "Format": [
    "3.0 (quilt)"
  ],
  "Homepage": [
    "http://live.gnome.org/Hyena"
  ],
  "Maintainer": [
    "Debian CLI Libraries Team \u003cpkg-cli-libs-team@lists.alioth.debian.org\u003e"
  ],
  "Package": [
    "hyena"
  ],
  "Package-List": [
    "libhyena-cil deb cli-mono optional arch=all libhyena-cil-dev deb cli-mono optional arch=all monodoc-hyena-manual deb doc optional arch=all"
  ],
  "Priority": [
    "source"
  ],
  "Section": [
    "cli-mono"
  ],
  "Standards-Version": [
    "3.9.5"
  ],
  "Uploaders": [
    "Chow Loong Jin \u003chyperair@debian.org\u003e"
  ],
  "Vcs-Browser": [
    "http://git.debian.org/?p=pkg-cli-libs/packages/hyena.git"
  ],
  "Vcs-Git": [
    "git://git.debian.org/git/pkg-cli-libs/packages/hyena.git"
  ],
  "Version": [
    "0.5-4"
  ]
}