{
  "Architecture": [
    "all"
  ],
  "Binary": [
    "node-elliptic"
  ],
  "Build-Depends": [
    "debhelper-compat (= 13), mocha \u003c!nocheck\u003e, node-assert \u003c!nocheck\u003e, node-bn.js \u003c!nocheck\u003e, node-brorand \u003c!nocheck\u003e, node-hash.js \u003c!nocheck\u003e, node-hmac-drbg \u003c!nocheck\u003e, node-inherits \u003c!nocheck\u003e, node-minimalistic-crypto-utils \u003c!nocheck\u003e, nodejs \u003c!nocheck\u003e"
  ],
  "Checksums-Sha256": [
    "f64ecb45e227abd96b6240b77596013f9a198ac77f16cae2601bcd24550065e6 2354 node-elliptic_6.6.1+dfsg-1.dsc 16ef544eaf9e76cebfe69f734b13030e34c9cc79ebeff60b254fe1d8612d2f79 857648 node-elliptic_6.6.1+dfsg.orig.tar.xz 9a3a94154e1a87ff9eef03371111e876991ac0c48c882b5c5dd04a328ae8e714 4344 node-elliptic_6.6.1+dfsg-1.debian.tar.xz"
  ],
  "Directory": [
    "pool/main/n/node-elliptic"
  ],
  "Files": [
    "f60e49aa4a0ffaa9b652bdfacbb12bfe 2354 node-elliptic_6.6.1+dfsg-1.dsc 2b102dba54f39b7f3e9dfb103072b129 857648 node-elliptic_6.6.1+dfsg.orig.tar.xz 3c5af6afaf4d8ffc4a66b3e27c7e234e 4344 node-elliptic_6.6.1+dfsg-1.debian.tar.xz"
  ],
  "Format": [
    "3.0 (quilt)"
  ],
  "Homepage": [
    "https://github.com/indutny/elliptic"
  ],
  "Maintainer": [
    "Debian Javascript Maintainers \u003cpkg-javascript-devel@lists.alioth.debian.org\u003e"
  ],
  "Package": [
    "node-elliptic"
  ],
  "Package-List": [
    "node-elliptic deb javascript optional arch=all"
  ],
  "Priority": [
    "optional"
  ],
  "Section": [
    "javascript"
  ],
  "Standards-Version": [
    "4.7.0"
  ],
  "Testsuite": [
    "autopkgtest"
  ],
  "Testsuite-Triggers": [
    "@builddeps@"
  ],
  "Uploaders": [
    "Jonas Smedegaard \u003cdr@jones.dk\u003e, Pirate Praveen \u003cpraveen@debian.org\u003e,"
  ],
  "Vcs-Browser": [
    "https://salsa.debian.org/js-team/node-elliptic"
  ],
  "Vcs-Git": [
    "https://salsa.debian.org/js-team/node-elliptic.git"
  ],
  "Version": [
    "6.6.1+dfsg-1"
  ]
}